terminal-preroll/__main__.py
terminal_preroll/__main__.py
terminal_preroll-1.0.dist-info/METADATA
terminal_preroll-1.0.dist-info/WHEEL
terminal_preroll-1.0.dist-info/top_level.txt
terminal_preroll-1.0.dist-info/RECORD
