Metadata-Version: 2.1
Name: terminal-preroll
Version: 1.0
Summary: Stream Preroll Animation for Python
Home-page: https://www.github.com/zadammac/terminal_preroll
Author: Zac Adam-MacEwen
Author-email: zadammac@kenshosec.com
License: UNKNOWN
Platform: UNKNOWN
Requires-Dist: blessings
Requires-Dist: termcolor
